pytest_xray_server/__init__.py
pytest_xray_server/constants.py
pytest_xray_server/models.py
pytest_xray_server/plugin.py
pytest_xray_server/utils.py
pytest_xray_server-1.6.dist-info/LICENSE
pytest_xray_server-1.6.dist-info/METADATA
pytest_xray_server-1.6.dist-info/WHEEL
pytest_xray_server-1.6.dist-info/entry_points.txt
pytest_xray_server-1.6.dist-info/top_level.txt
pytest_xray_server-1.6.dist-info/RECORD
