Metadata-Version: 2.1
Name: pytest-xray-server
Version: 1.6
Summary: UNKNOWN
Download-URL: https://github.com/lexa/pytest-xray-server/archive/v1.4.tar.gz
Author: Neville Tummon
Author-email: nt.devs@gmail.com
Maintainer: Yuliya Sharkadiy
Maintainer-email: yuliya@sharky.email
License: UNKNOWN
Platform: UNKNOWN
Classifier: Development Status :: 3 - Alpha
Classifier: Intended Audience :: Developers
Classifier: Topic :: Software Development :: Testing
Classifier: License :: OSI Approved :: MIT License
Classifier: Programming Language :: Python :: 3
Classifier: Programming Language :: Python :: 3.6
Classifier: Programming Language :: Python :: 3.7
Classifier: Programming Language :: Python :: 3.8
Classifier: Programming Language :: Python :: 3.9
Classifier: Programming Language :: Python :: Implementation :: CPython
Requires-Python: >=3.6.6
License-File: LICENSE
Requires-Dist: pytest (>=5.3.1)
Requires-Dist: requests (>=2.21.4)
